{
  "minecraft:recipes/combat/wooden_sword": {
    "criteria": {
      "has_stick": "2021-12-04 17:05:30 +0100"
    },
    "done": true
  },
  "biomesoplenty:recipes/transportation/boat_ethereal": {
    "criteria": {
      "entered_water": "2021-12-04 16:37:22 +0100"
    },
    "done": true
  },
  "biomesoplenty:recipes/transportation/boat_mahogany": {
    "criteria": {
      "entered_water": "2021-12-04 16:37:22 +0100"
    },
    "done": true
  },
  "minecraft:recipes/tools/wooden_axe": {
    "criteria": {
      "has_stick": "2021-12-04 17:05:30 +0100"
    },
    "done": true
  },
  "biomesoplenty:recipes/transportation/boat_cherry": {
    "criteria": {
      "entered_water": "2021-12-04 16:37:22 +0100"
    },
    "done": true
  },
  "minecraft:recipes/transportation/dark_oak_boat": {
    "criteria": {
      "entered_water": "2021-12-04 16:37:22 +0100"
    },
    "done": true
  },
  "biomesoplenty:recipes/transportation/boat_jacaranda": {
    "criteria": {
      "entered_water": "2021-12-04 16:37:22 +0100"
    },
    "done": true
  },
  "biomesoplenty:recipes/transportation/boat_umbran": {
    "criteria": {
      "entered_water": "2021-12-04 16:37:22 +0100"
    },
    "done": true
  },
  "minecraft:recipes/food/cake": {
    "criteria": {
      "has_egg": "2021-12-04 17:07:28 +0100"
    },
    "done": true
  },
  "mysticalworld:root": {
    "criteria": {
      "auto": "2021-12-04 16:01:48 +0100"
    },
    "done": true
  },
  "astralsorcery:root": {
    "criteria": {
      "astralsorcery_present": "2021-12-04 16:01:48 +0100"
    },
    "done": true
  },
  "minecraft:recipes/tools/wooden_hoe": {
    "criteria": {
      "has_stick": "2021-12-04 17:05:30 +0100"
    },
    "done": true
  },
  "minecraft:adventure/adventuring_time": {
    "criteria": {
      "forest": "2021-12-04 16:01:48 +0100",
      "extreme_hills": "2021-12-04 16:37:24 +0100",
      "river": "2021-12-04 16:37:23 +0100"
    },
    "done": false
  },
  "biomesoplenty:recipes/transportation/boat_fir": {
    "criteria": {
      "entered_water": "2021-12-04 16:37:22 +0100"
    },
    "done": true
  },
  "simplyjetpacks:vanilla/root_vanilla": {
    "criteria": {
      "code_trigger": "2021-12-04 16:01:48 +0100"
    },
    "done": true
  },
  "minecraft:recipes/tools/wooden_pickaxe": {
    "criteria": {
      "has_stick": "2021-12-04 17:05:30 +0100"
    },
    "done": true
  },
  "simplyjetpacks:ie/root_ie": {
    "criteria": {
      "code_trigger": "2021-12-04 16:01:48 +0100"
    },
    "done": true
  },
  "minecraft:recipes/decorations/ladder": {
    "criteria": {
      "has_stick": "2021-12-04 17:05:30 +0100"
    },
    "done": true
  },
  "minecraft:husbandry/root": {
    "criteria": {
      "consumed_item": "2021-12-04 17:08:00 +0100"
    },
    "done": true
  },
  "simplyjetpacks:te/root_te": {
    "criteria": {
      "code_trigger": "2021-12-04 16:01:48 +0100"
    },
    "done": true
  },
  "minecraft:recipes/decorations/chest": {
    "criteria": {
      "has_lots_of_items": "2021-12-04 16:34:45 +0100"
    },
    "done": true
  },
  "biomesoplenty:recipes/transportation/boat_magic": {
    "criteria": {
      "entered_water": "2021-12-04 16:37:22 +0100"
    },
    "done": true
  },
  "minecraft:recipes/transportation/birch_boat": {
    "criteria": {
      "entered_water": "2021-12-04 16:37:22 +0100"
    },
    "done": true
  },
  "biomesoplenty:recipes/transportation/boat_ebony": {
    "criteria": {
      "entered_water": "2021-12-04 16:37:22 +0100"
    },
    "done": true
  },
  "biomesoplenty:recipes/transportation/boat_hellbark": {
    "criteria": {
      "entered_water": "2021-12-04 16:37:22 +0100"
    },
    "done": true
  },
  "biomesoplenty:recipes/transportation/boat_willow": {
    "criteria": {
      "entered_water": "2021-12-04 16:37:22 +0100"
    },
    "done": true
  },
  "buildcraftcore:root": {
    "criteria": {
      "has_stick": "2021-12-04 17:05:30 +0100"
    },
    "done": true
  },
  "simplyjetpacks:root": {
    "criteria": {
      "code_trigger": "2021-12-04 16:01:48 +0100"
    },
    "done": true
  },
  "biomesoplenty:recipes/transportation/boat_sacred_oak": {
    "criteria": {
      "entered_water": "2021-12-04 16:37:22 +0100"
    },
    "done": true
  },
  "minecraft:recipes/tools/wooden_shovel": {
    "criteria": {
      "has_stick": "2021-12-04 17:05:30 +0100"
    },
    "done": true
  },
  "integrateddynamics:root": {
    "criteria": {
      "criteria_0": "2021-12-04 16:02:09 +0100"
    },
    "done": true
  },
  "biomesoplenty:recipes/transportation/boat_mangrove": {
    "criteria": {
      "entered_water": "2021-12-04 16:37:22 +0100"
    },
    "done": true
  },
  "minecraft:recipes/transportation/acacia_boat": {
    "criteria": {
      "entered_water": "2021-12-04 16:37:22 +0100"
    },
    "done": true
  },
  "biomesoplenty:recipes/transportation/boat_pine": {
    "criteria": {
      "entered_water": "2021-12-04 16:37:22 +0100"
    },
    "done": true
  },
  "biomesoplenty:recipes/transportation/boat_palm": {
    "criteria": {
      "entered_water": "2021-12-04 16:37:22 +0100"
    },
    "done": true
  },
  "nuclearcraft:root": {
    "criteria": {
      "location": "2021-12-04 16:01:48 +0100"
    },
    "done": true
  },
  "simplyjetpacks:eio/root_eio": {
    "criteria": {
      "code_trigger": "2021-12-04 16:01:48 +0100"
    },
    "done": true
  },
  "biomesoplenty:recipes/transportation/boat_redwood": {
    "criteria": {
      "entered_water": "2021-12-04 16:37:22 +0100"
    },
    "done": true
  },
  "galacticraftcore:galacticraft/root": {
    "criteria": {
      "tick": "2021-12-04 16:01:48 +0100"
    },
    "done": true
  },
  "minecraft:adventure/root": {
    "criteria": {
      "killed_by_something": "2021-12-04 16:10:17 +0100"
    },
    "done": true
  },
  "minecraft:recipes/transportation/boat": {
    "criteria": {
      "entered_water": "2021-12-04 16:37:22 +0100"
    },
    "done": true
  },
  "biomesoplenty:recipes/transportation/boat_eucalyptus": {
    "criteria": {
      "entered_water": "2021-12-04 16:37:22 +0100"
    },
    "done": true
  },
  "minecraft:recipes/transportation/jungle_boat": {
    "criteria": {
      "entered_water": "2021-12-04 16:37:22 +0100"
    },
    "done": true
  },
  "minecraft:recipes/transportation/spruce_boat": {
    "criteria": {
      "entered_water": "2021-12-04 16:37:22 +0100"
    },
    "done": true
  },
  "twilightforest:alt/compat/tconstruct": {
    "criteria": {
      "book": "2021-12-04 16:02:34 +0100"
    },
    "done": true
  },
  "mystcraft:root": {
    "criteria": {
      "mystcraft_present": "2021-12-04 16:01:48 +0100"
    },
    "done": true
  }
}